[
  {
    "id": "need:00",
    "token_class": "NEED",
    "phase": "ANY",
    "attractor_weights": [
      0.324,
      0.261,
      0.097,
      0.607,
      0.005,
      0.352
    ],
    "affinity_tags": [
      "tag_0"
    ],
    "repulsion_tags": [],
    "temperature": 0.898,
    "narrative_gradient": 0.0,
    "is_invariant": false,
    "surface_expression": ""
  },
  {
    "id": "state:01",
    "token_class": "STATE",
    "phase": "ANY",
    "attractor_weights": [
      0.057,
      0.388,
      0.432,
      0.029,
      0.265,
      0.492
    ],
    "affinity_tags": [
      "tag_1"
    ],
    "repulsion_tags": [],
    "temperature": 0.452,
    "narrative_gradient": 0.0,
    "is_invariant": false,
    "surface_expression": ""
  },
  {
    "id": "time:02",
    "token_class": "TIME",
    "phase": "ANY",
    "attractor_weights": [
      0.508,
      0.11,
      0.167,
      0.078,
      0.354,
      0.647
    ],
    "affinity_tags": [
      "tag_2"
    ],
    "repulsion_tags": [],
    "temperature": 0.59,
    "narrative_gradient": 0.0,
    "is_invariant": false,
    "surface_expression": ""
  },
  {
    "id": "offering:03",
    "token_class": "OFFERING",
    "phase": "ANY",
    "attractor_weights": [
      0.542,
      0.269,
      0.522,
      0.071,
      0.204,
      0.472
    ],
    "affinity_tags": [
      "tag_3"
    ],
    "repulsion_tags": [],
    "temperature": 0.726,
    "narrative_gradient": 0.0,
    "is_invariant": false,
    "surface_expression": ""
  },
  {
    "id": "need:04",
    "token_class": "NEED",
    "phase": "ANY",
    "attractor_weights": [
      0.295,
      0.061,
      0.187,
      0.147,
      0.197,
      0.567
    ],
    "affinity_tags": [
      "tag_4"
    ],
    "repulsion_tags": [],
    "temperature": 0.199,
    "narrative_gradient": 0.0,
    "is_invariant": false,
    "surface_expression": ""
  },
  {
    "id": "state:05",
    "token_class": "STATE",
    "phase": "ANY",
    "attractor_weights": [
      0.62,
      0.616,
      0.038,
      0.265,
      0.344,
      0.016
    ],
    "affinity_tags": [
      "tag_5"
    ],
    "repulsion_tags": [],
    "temperature": 0.425,
    "narrative_gradient": 0.0,
    "is_invariant": false,
    "surface_expression": ""
  },
  {
    "id": "time:06",
    "token_class": "TIME",
    "phase": "ANY",
    "attractor_weights": [
      0.634,
      0.078,
      0.418,
      0.085,
      0.405,
      0.627
    ],
    "affinity_tags": [
      "tag_0"
    ],
    "repulsion_tags": [],
    "temperature": 0.203,
    "narrative_gradient": 0.0,
    "is_invariant": false,
    "surface_expression": ""
  },
  {
    "id": "offering:07",
    "token_class": "OFFERING",
    "phase": "ANY",
    "attractor_weights": [
      0.006,
      0.058,
      0.378,
      0.012,
      0.059,
      0.348
    ],
    "affinity_tags": [
      "tag_1"
    ],
    "repulsion_tags": [],
    "temperature": 0.921,
    "narrative_gradient": 0.0,
    "is_invariant": false,
    "surface_expression": ""
  },
  {
    "id": "need:08",
    "token_class": "NEED",
    "phase": "ANY",
    "attractor_weights": [
      0.294,
      0.279,
      0.447,
      0.065,
      0.406,
      0.121
    ],
    "affinity_tags": [
      "tag_2"
    ],
    "repulsion_tags": [],
    "temperature": 0.609,
    "narrative_gradient": 0.0,
    "is_invariant": false,
    "surface_expression": ""
  },
  {
    "id": "state:09",
    "token_class": "STATE",
    "phase": "ANY",
    "attractor_weights": [
      0.671,
      0.038,
      0.389,
      0.424,
      0.105,
      0.188
    ],
    "affinity_tags": [
      "tag_3"
    ],
    "repulsion_tags": [],
    "temperature": 0.995,
    "narrative_gradient": 0.0,
    "is_invariant": false,
    "surface_expression": ""
  },
  {
    "id": "time:10",
    "token_class": "TIME",
    "phase": "ANY",
    "attractor_weights": [
      0.699,
      0.085,
      0.494,
      0.666,
      0.166,
      0.428
    ],
    "affinity_tags": [
      "tag_4"
    ],
    "repulsion_tags": [],
    "temperature": 0.043,
    "narrative_gradient": 0.0,
    "is_invariant": false,
    "surface_expression": ""
  },
  {
    "id": "offering:11",
    "token_class": "OFFERING",
    "phase": "ANY",
    "attractor_weights": [
      0.256,
      0.472,
      0.413,
      0.542,
      0.061,
      0.243
    ],
    "affinity_tags": [
      "tag_5"
    ],
    "repulsion_tags": [],
    "temperature": 0.864,
    "narrative_gradient": 0.0,
    "is_invariant": false,
    "surface_expression": ""
  },
  {
    "id": "need:12",
    "token_class": "NEED",
    "phase": "ANY",
    "attractor_weights": [
      0.409,
      0.316,
      0.282,
      0.69,
      0.402,
      0.013
    ],
    "affinity_tags": [
      "tag_0"
    ],
    "repulsion_tags": [],
    "temperature": 0.799,
    "narrative_gradient": 0.0,
    "is_invariant": false,
    "surface_expression": ""
  },
  {
    "id": "state:13",
    "token_class": "STATE",
    "phase": "ANY",
    "attractor_weights": [
      0.23,
      0.304,
      0.149,
      0.311,
      0.227,
      0.062
    ],
    "affinity_tags": [
      "tag_1"
    ],
    "repulsion_tags": [],
    "temperature": 0.63,
    "narrative_gradient": 0.0,
    "is_invariant": false,
    "surface_expression": ""
  },
  {
    "id": "time:14",
    "token_class": "TIME",
    "phase": "ANY",
    "attractor_weights": [
      0.072,
      0.549,
      0.018,
      0.547,
      0.565,
      0.348
    ],
    "affinity_tags": [
      "tag_2"
    ],
    "repulsion_tags": [],
    "temperature": 0.709,
    "narrative_gradient": 0.0,
    "is_invariant": false,
    "surface_expression": ""
  },
  {
    "id": "offering:15",
    "token_class": "OFFERING",
    "phase": "ANY",
    "attractor_weights": [
      0.174,
      0.516,
      0.298,
      0.162,
      0.675,
      0.281
    ],
    "affinity_tags": [
      "tag_3"
    ],
    "repulsion_tags": [],
    "temperature": 0.373,
    "narrative_gradient": 0.0,
    "is_invariant": false,
    "surface_expression": ""
  },
  {
    "id": "need:16",
    "token_class": "NEED",
    "phase": "ANY",
    "attractor_weights": [
      0.602,
      0.259,
      0.467,
      0.12,
      0.59,
      0.181
    ],
    "affinity_tags": [
      "tag_4"
    ],
    "repulsion_tags": [],
    "temperature": 0.051,
    "narrative_gradient": 0.0,
    "is_invariant": false,
    "surface_expression": ""
  },
  {
    "id": "state:17",
    "token_class": "STATE",
    "phase": "ANY",
    "attractor_weights": [
      0.683,
      0.121,
      0.663,
      0.69,
      0.425,
      0.008
    ],
    "affinity_tags": [
      "tag_5"
    ],
    "repulsion_tags": [],
    "temperature": 0.061,
    "narrative_gradient": 0.0,
    "is_invariant": false,
    "surface_expression": ""
  },
  {
    "id": "time:18",
    "token_class": "TIME",
    "phase": "ANY",
    "attractor_weights": [
      0.146,
      0.272,
      0.428,
      0.677,
      0.248,
      0.098
    ],
    "affinity_tags": [
      "tag_0"
    ],
    "repulsion_tags": [],
    "temperature": 0.562,
    "narrative_gradient": 0.0,
    "is_invariant": false,
    "surface_expression": ""
  },
  {
    "id": "offering:19",
    "token_class": "OFFERING",
    "phase": "ANY",
    "attractor_weights": [
      0.096,
      0.061,
      0.389,
      0.487,
      0.046,
      0.316
    ],
    "affinity_tags": [
      "tag_1"
    ],
    "repulsion_tags": [],
    "temperature": 0.704,
    "narrative_gradient": 0.0,
    "is_invariant": false,
    "surface_expression": ""
  },
  {
    "id": "need:20",
    "token_class": "NEED",
    "phase": "ANY",
    "attractor_weights": [
      0.535,
      0.268,
      0.621,
      0.118,
      0.501,
      0.54
    ],
    "affinity_tags": [
      "tag_2"
    ],
    "repulsion_tags": [],
    "temperature": 0.88,
    "narrative_gradient": 0.0,
    "is_invariant": false,
    "surface_expression": ""
  },
  {
    "id": "state:21",
    "token_class": "STATE",
    "phase": "ANY",
    "attractor_weights": [
      0.346,
      0.069,
      0.034,
      0.37,
      0.121,
      0.441
    ],
    "affinity_tags": [
      "tag_3"
    ],
    "repulsion_tags": [],
    "temperature": 0.084,
    "narrative_gradient": 0.0,
    "is_invariant": false,
    "surface_expression": ""
  },
  {
    "id": "time:22",
    "token_class": "TIME",
    "phase": "ANY",
    "attractor_weights": [
      0.546,
      0.156,
      0.009,
      0.123,
      0.32,
      0.391
    ],
    "affinity_tags": [
      "tag_4"
    ],
    "repulsion_tags": [],
    "temperature": 0.388,
    "narrative_gradient": 0.0,
    "is_invariant": false,
    "surface_expression": ""
  },
  {
    "id": "offering:23",
    "token_class": "OFFERING",
    "phase": "ANY",
    "attractor_weights": [
      0.121,
      0.337,
      0.663,
      0.375,
      0.659,
      0.02
    ],
    "affinity_tags": [
      "tag_5"
    ],
    "repulsion_tags": [],
    "temperature": 0.993,
    "narrative_gradient": 0.0,
    "is_invariant": false,
    "surface_expression": ""
  },
  {
    "id": "need:24",
    "token_class": "NEED",
    "phase": "ANY",
    "attractor_weights": [
      0.622,
      0.381,
      0.366,
      0.376,
      0.637,
      0.046
    ],
    "affinity_tags": [
      "tag_0"
    ],
    "repulsion_tags": [],
    "temperature": 0.643,
    "narrative_gradient": 0.0,
    "is_invariant": false,
    "surface_expression": ""
  },
  {
    "id": "state:25",
    "token_class": "STATE",
    "phase": "ANY",
    "attractor_weights": [
      0.38,
      0.21,
      0.507,
      0.504,
      0.072,
      0.49
    ],
    "affinity_tags": [
      "tag_1"
    ],
    "repulsion_tags": [],
    "temperature": 0.454,
    "narrative_gradient": 0.0,
    "is_invariant": false,
    "surface_expression": ""
  },
  {
    "id": "time:26",
    "token_class": "TIME",
    "phase": "ANY",
    "attractor_weights": [
      0.343,
      0.446,
      0.037,
      0.422,
      0.261,
      0.615
    ],
    "affinity_tags": [
      "tag_2"
    ],
    "repulsion_tags": [],
    "temperature": 0.231,
    "narrative_gradient": 0.0,
    "is_invariant": false,
    "surface_expression": ""
  },
  {
    "id": "offering:27",
    "token_class": "OFFERING",
    "phase": "ANY",
    "attractor_weights": [
      0.576,
      0.511,
      0.437,
      0.613,
      0.025,
      0.418
    ],
    "affinity_tags": [
      "tag_3"
    ],
    "repulsion_tags": [],
    "temperature": 0.613,
    "narrative_gradient": 0.0,
    "is_invariant": false,
    "surface_expression": ""
  },
  {
    "id": "need:28",
    "token_class": "NEED",
    "phase": "ANY",
    "attractor_weights": [
      0.475,
      0.285,
      0.048,
      0.132,
      0.426,
      0.127
    ],
    "affinity_tags": [
      "tag_4"
    ],
    "repulsion_tags": [],
    "temperature": 0.065,
    "narrative_gradient": 0.0,
    "is_invariant": false,
    "surface_expression": ""
  },
  {
    "id": "state:29",
    "token_class": "STATE",
    "phase": "ANY",
    "attractor_weights": [
      0.248,
      0.329,
      0.375,
      0.018,
      0.543,
      0.234
    ],
    "affinity_tags": [
      "tag_5"
    ],
    "repulsion_tags": [],
    "temperature": 0.783,
    "narrative_gradient": 0.0,
    "is_invariant": false,
    "surface_expression": ""
  },
  {
    "id": "time:30",
    "token_class": "TIME",
    "phase": "ANY",
    "attractor_weights": [
      0.006,
      0.668,
      0.413,
      0.683,
      0.69,
      0.583
    ],
    "affinity_tags": [
      "tag_0"
    ],
    "repulsion_tags": [],
    "temperature": 0.106,
    "narrative_gradient": 0.0,
    "is_invariant": false,
    "surface_expression": ""
  },
  {
    "id": "offering:31",
    "token_class": "OFFERING",
    "phase": "ANY",
    "attractor_weights": [
      0.244,
      0.162,
      0.546,
      0.135,
      0.155,
      0.077
    ],
    "affinity_tags": [
      "tag_1"
    ],
    "repulsion_tags": [],
    "temperature": 0.12,
    "narrative_gradient": 0.0,
    "is_invariant": false,
    "surface_expression": ""
  }
]